netCDF4/__init__.py
netCDF4/__init__.pyi
netCDF4/_netCDF4.cpython-310-x86_64-linux-gnu.so
netCDF4/_netCDF4.pyi
netCDF4/_netCDF4.pyx
netCDF4/py.typed
netCDF4/utils.py
netCDF4/plugins/empty.txt
netcdf4.libs/libaec-187855bc.so.0.1.3
netcdf4.libs/libcrypto-fa417996.so.3
netcdf4.libs/libcurl-69c0d65e.so.4.8.0
netcdf4.libs/libhdf5-49234e76.so.310.5.1
netcdf4.libs/libhdf5_hl-0ce065ed.so.310.0.6
netcdf4.libs/libnetcdf-306d3f1b.so.22
netcdf4.libs/libssl-6faad603.so.3
netcdf4.libs/libsz-daeb5235.so.2.0.1
netcdf4-1.7.3.dist-info/METADATA
netcdf4-1.7.3.dist-info/WHEEL
netcdf4-1.7.3.dist-info/entry_points.txt
netcdf4-1.7.3.dist-info/top_level.txt
netcdf4-1.7.3.dist-info/RECORD
netcdf4-1.7.3.dist-info/licenses/LICENSE
