Metadata-Version: 2.4
Name: netCDF4
Version: 1.7.3
Summary: Provides an object-oriented python interface to the netCDF version 4 library
Author-email: Jeff Whitaker <whitaker.jeffrey@gmail.com>
License-Expression: MIT
Project-URL: Documentation, https://unidata.github.io/netcdf4-python/
Project-URL: Repository, https://github.com/Unidata/netcdf4-python
Keywords: numpy,netcdf,data,science,network,oceanography,meteorology,climate
Classifier: Development Status :: 3 - Alpha
Classifier: Programming Language :: Python :: 3
Classifier: Programming Language :: Python :: 3.10
Classifier: Programming Language :: Python :: 3.11
Classifier: Programming Language :: Python :: 3.12
Classifier: Programming Language :: Python :: 3.13
Classifier: Programming Language :: Python :: 3.14
Classifier: Intended Audience :: Science/Research
Classifier: Topic :: Software Development :: Libraries :: Python Modules
Classifier: Topic :: System :: Archiving :: Compression
Classifier: Operating System :: OS Independent
Requires-Python: >=3.10
License-File: LICENSE
Requires-Dist: cftime
Requires-Dist: certifi
Requires-Dist: numpy
Provides-Extra: tests
Requires-Dist: Cython; extra == "tests"
Requires-Dist: packaging; extra == "tests"
Requires-Dist: pytest; extra == "tests"
Requires-Dist: typing-extensions>=4.15.0; extra == "tests"
Provides-Extra: parallel
Requires-Dist: mpi4py; extra == "parallel"
Dynamic: license-file
